[
    {
        "userId": 1,
        "username": "user1",
        "password": "pass",
        "type": "customer",
        "balance": 500
        
    },
    {
       "userId": 2,
       "username": "user2",
       "password": "pass",
       "type": "seller"
    }
,
    {
        "userId": 3,
        "username": "user3",
        "password": "pass",
        "type": "customer",
        "balance": 500
        
    },
    {
       "userId": 4,
       "username": "user4",
       "password": "pass",
       "type": "seller"
    }
,
    {
        "userId": 5,
        "username": "user5",
        "password": "pass",
        "type": "customer",
        "balance": 500
        
    },
    {
       "userId": 6,
       "username": "user6",
       "password": "pass",
       "type": "seller"
    }
]
